dunder_run/__init__.py
dunder_run/__main__.py
dunder_run-0.1.0.dist-info/LICENSE
dunder_run-0.1.0.dist-info/METADATA
dunder_run-0.1.0.dist-info/WHEEL
dunder_run-0.1.0.dist-info/entry_points.txt
dunder_run-0.1.0.dist-info/top_level.txt
dunder_run-0.1.0.dist-info/RECORD
