Metadata-Version: 2.1
Name: dunder-run
Version: 0.1.0
Summary: A proof-of-concept for a new way of running Python scripts.
Home-page: https://github.com/scaramagus/dunder-run
Author: Agustin Scaramuzza
Author-email: agustinscaramuzza@gmail.com
License: GPLv3
Platform: UNKNOWN
